raebot/__init__.py
raebot/model.py
raebot/query.py
raebot-0.2.0.dist-info/METADATA
raebot-0.2.0.dist-info/WHEEL
raebot-0.2.0.dist-info/RECORD
